pelican_fontawesome/__init__.py
pelican_fontawesome/fontawesome.py
pelican_fontawesome-0.1.0.dist-info/zip-safe
pelican_fontawesome-0.1.0.dist-info/DESCRIPTION.rst
pelican_fontawesome-0.1.0.dist-info/RECORD
pelican_fontawesome-0.1.0.dist-info/METADATA
pelican_fontawesome-0.1.0.dist-info/metadata.json
pelican_fontawesome-0.1.0.dist-info/WHEEL
pelican_fontawesome-0.1.0.dist-info/top_level.txt
